{
  "IcoMoonType": "selection",
  "icons": [
    {
      "icon": {
        "paths": [
          "M204.8 0l672.914 629.029 672.914-629.029 204.8 190.171-877.714 833.829-877.714-833.829 204.8-190.171z"
        ],
        "attrs": [
          {}
        ],
        "width": 1755,
        "isMulticolor": false,
        "isMulticolor2": false,
        "grid": 0,
        "tags": [
          "angle-down"
        ],
        "colorPermutations": {
          "16821217512542542541611101": [
            {}
          ]
        }
      },
      "attrs": [
        {}
      ],
      "properties": {
        "order": 55,
        "id": 29,
        "name": "angle-down",
        "prevSize": 32
      },
      "setIdx": 0,
      "setId": 2,
      "iconIdx": 0
    },
    {
      "icon": {
        "paths": [
          "M597.333 119.467l-366.933 392.533 366.933 392.533-110.933 119.467-486.4-512 486.4-512 110.933 119.467z"
        ],
        "attrs": [
          {}
        ],
        "width": 597,
        "isMulticolor": false,
        "isMulticolor2": false,
        "grid": 0,
        "tags": [
          "angle-left"
        ],
        "colorPermutations": {
          "16821217512542542541611101": [
            {}
          ]
        }
      },
      "attrs": [
        {}
      ],
      "properties": {
        "order": 56,
        "id": 28,
        "name": "angle-left",
        "prevSize": 32
      },
      "setIdx": 0,
      "setId": 2,
      "iconIdx": 1
    },
    {
      "icon": {
        "paths": [
          "M0 904.533l366.933-392.533-366.933-392.533 110.933-119.467 486.4 512-486.4 512-110.933-119.467z"
        ],
        "attrs": [
          {}
        ],
        "width": 597,
        "isMulticolor": false,
        "isMulticolor2": false,
        "grid": 0,
        "tags": [
          "angle-right"
        ],
        "colorPermutations": {
          "16821217512542542541611101": [
            {}
          ]
        }
      },
      "attrs": [
        {}
      ],
      "properties": {
        "order": 57,
        "id": 27,
        "name": "angle-right",
        "prevSize": 32
      },
      "setIdx": 0,
      "setId": 2,
      "iconIdx": 2
    },
    {
      "icon": {
        "paths": [
          "M1550.629 1024l-672.914-629.029-672.914 629.029-204.8-190.171 877.714-833.829 877.714 833.829-204.8 190.171z"
        ],
        "attrs": [
          {}
        ],
        "width": 1755,
        "isMulticolor": false,
        "isMulticolor2": false,
        "grid": 0,
        "tags": [
          "angle-up"
        ],
        "colorPermutations": {
          "16821217512542542541611101": [
            {}
          ]
        }
      },
      "attrs": [
        {}
      ],
      "properties": {
        "order": 58,
        "id": 26,
        "name": "angle-up",
        "prevSize": 32
      },
      "setIdx": 0,
      "setId": 2,
      "iconIdx": 3
    },
    {
      "icon": {
        "paths": [
          "M19.2 96c12.8-12.8 25.6-19.2 44.8-19.2 38.4 0 64 25.6 64 64v665.6l787.2-787.2c25.6-25.6 64-25.6 89.6 0s25.6 64 0 89.6l-787.2 787.2h665.6c38.4 0 64 25.6 64 64s-25.6 64-64 64h-819.2c0 0 0 0 0 0v0c0 0 0 0 0 0v0c0 0 0 0 0 0s0 0 0 0 0 0 0 0v0c0 0 0 0 0 0v0c0 0 0 0 0 0-6.4 0-19.2 0-25.6-6.4-6.4 0-12.8-6.4-19.2-12.8 0 0 0 0 0 0v0c0 0 0 0 0 0v0c0 0 0 0 0 0-6.4-6.4-6.4-12.8-12.8-19.2s-6.4-19.2-6.4-25.6v0-819.2c0-19.2 6.4-32 19.2-44.8z"
        ],
        "attrs": [
          {}
        ],
        "isMulticolor": false,
        "isMulticolor2": false,
        "grid": 0,
        "tags": [
          "arrow-2-bottom-left-45"
        ],
        "colorPermutations": {
          "16821217512542542541611101": [
            {}
          ]
        }
      },
      "attrs": [
        {}
      ],
      "properties": {
        "order": 59,
        "id": 25,
        "name": "arrow-2-bottom-left-45",
        "prevSize": 32
      },
      "setIdx": 0,
      "setId": 2,
      "iconIdx": 4
    },
    {
      "icon": {
        "paths": [
          "M0 554.275c0-14.092 4.697-23.486 14.092-32.881 18.789-18.789 46.972-18.789 65.761 0l342.899 342.899v-817.321c0-28.183 18.789-46.972 46.972-46.972s46.972 18.789 46.972 46.972v817.321l342.899-342.899c18.789-18.789 46.972-18.789 65.761 0s18.789 46.972 0 65.761l-422.752 422.752c0 0 0 0 0 0v0c0 0 0 0 0 0v0c0 0 0 0 0 0s0 0 0 0 0 0 0 0v0c0 0 0 0 0 0v0c0 0 0 0 0 0-4.697 4.697-9.394 9.394-14.092 9.394s-9.394 4.697-14.092 4.697c0 0 0 0 0 0v0c0 0 0 0-4.697 0v0c0 0 0 0 0 0-4.697 0-9.394 0-14.092-4.697-4.697 0-9.394-4.697-14.092-9.394v0l-422.752-422.752c-14.092-9.394-18.789-23.486-18.789-32.881z"
        ],
        "attrs": [
          {}
        ],
        "width": 944,
        "isMulticolor": false,
        "isMulticolor2": false,
        "grid": 0,
        "tags": [
          "arrow-2-down"
        ],
        "colorPermutations": {
          "16821217512542542541611101": [
            {}
          ]
        }
      },
      "attrs": [
        {}
      ],
      "properties": {
        "order": 60,
        "id": 24,
        "name": "arrow-2-down",
        "prevSize": 32
      },
      "setIdx": 0,
      "setId": 2,
      "iconIdx": 5
    },
    {
      "icon": {
        "paths": [
          "M509.453 0c15.284 0 25.473 5.095 35.662 15.284 20.378 20.378 20.378 50.945 0 71.323l-371.9 371.9h886.448c30.567 0 50.945 20.378 50.945 50.945s-20.378 50.945-50.945 50.945h-886.448l371.9 371.9c20.378 20.378 20.378 50.945 0 71.323s-50.945 20.378-71.323 0l-458.507-458.507c0 0 0 0 0 0v0c0 0 0 0 0 0v0c0 0 0 0 0 0s0 0 0 0 0 0 0 0v0c0 0 0 0 0 0v0c0 0 0 0 0 0-5.095-5.095-10.189-10.189-10.189-15.284-5.095-5.095-5.095-10.189-5.095-15.284 0 0 0 0 0 0v0c0 0 0 0 0-5.095v0c0 0 0 0 0 0 0-5.095 0-10.189 5.095-15.284 0-5.095 5.095-10.189 10.189-15.284v0l458.507-458.507c10.189-15.284 25.473-20.378 35.662-20.378z"
        ],
        "attrs": [
          {}
        ],
        "width": 1111,
        "isMulticolor": false,
        "isMulticolor2": false,
        "grid": 0,
        "tags": [
          "arrow-2-left"
        ],
        "colorPermutations": {
          "16821217512542542541611101": [
            {}
          ]
        }
      },
      "attrs": [
        {}
      ],
      "properties": {
        "order": 61,
        "id": 23,
        "name": "arrow-2-left",
        "prevSize": 32
      },
      "setIdx": 0,
      "setId": 2,
      "iconIdx": 6
    },
    {
      "icon": {
        "paths": [
          "M601.154 1024c-15.284 0-25.473-5.095-35.662-15.284-20.378-20.378-20.378-50.945 0-71.323l371.9-371.9h-886.448c-30.567 0-50.945-20.378-50.945-50.945s20.378-50.945 50.945-50.945h886.448l-371.9-371.9c-20.378-20.378-20.378-50.945 0-71.323s50.945-20.378 71.323 0l458.507 458.507c0 0 0 0 0 0v0c0 0 0 0 0 0v0c0 0 0 0 0 0s0 0 0 0 0 0 0 0v0c0 0 0 0 0 0v0c0 0 0 0 0 0 5.095 5.095 10.189 10.189 10.189 15.284s5.095 10.189 5.095 15.284c0 0 0 0 0 0v0c0 0 0 0 0 5.095v0c0 0 0 0 0 0 0 5.095 0 10.189-5.095 15.284 0 5.095-5.095 10.189-10.189 15.284v0l-458.507 458.507c-10.189 15.284-25.473 20.378-35.662 20.378z"
        ],
        "attrs": [
          {}
        ],
        "width": 1111,
        "isMulticolor": false,
        "isMulticolor2": false,
        "grid": 0,
        "tags": [
          "arrow-2-right"
        ],
        "colorPermutations": {
          "16821217512542542541611101": [
            {}
          ]
        }
      },
      "attrs": [
        {}
      ],
      "properties": {
        "order": 62,
        "id": 22,
        "name": "arrow-2-right",
        "prevSize": 32
      },
      "setIdx": 0,
      "setId": 2,
      "iconIdx": 7
    },
    {
      "icon": {
        "paths": [
          "M1004.8 928c-12.8 12.8-25.6 19.2-44.8 19.2-38.4 0-64-25.6-64-64v-665.6l-787.2 787.2c-25.6 25.6-64 25.6-89.6 0s-25.6-64 0-89.6l787.2-787.2h-665.6c-38.4 0-64-25.6-64-64s25.6-64 64-64h819.2c0 0 0 0 0 0v0c0 0 0 0 0 0v0c0 0 0 0 0 0s0 0 0 0 0 0 0 0v0c0 0 0 0 0 0v0c0 0 0 0 0 0 6.4 0 19.2 0 25.6 6.4 6.4 0 12.8 6.4 19.2 12.8 0 0 0 0 0 0v0c0 0 0 0 0 0v0c0 0 0 0 0 0 6.4 6.4 6.4 12.8 12.8 19.2s6.4 19.2 6.4 25.6v0 819.2c0 19.2-6.4 32-19.2 44.8z"
        ],
        "attrs": [
          {}
        ],
        "isMulticolor": false,
        "isMulticolor2": false,
        "grid": 0,
        "tags": [
          "arrow-2-top-right-45"
        ],
        "colorPermutations": {
          "16821217512542542541611101": [
            {}
          ]
        }
      },
      "attrs": [
        {}
      ],
      "properties": {
        "order": 63,
        "id": 21,
        "name": "arrow-2-top-right-45",
        "prevSize": 32
      },
      "setIdx": 0,
      "setId": 2,
      "iconIdx": 8
    },
    {
      "icon": {
        "paths": [
          "M944.147 469.725c0 14.092-4.697 23.486-14.092 32.881-18.789 18.789-46.972 18.789-65.761 0l-347.596-342.899v817.321c0 28.183-18.789 46.972-46.972 46.972s-46.972-18.789-46.972-46.972v-817.321l-342.899 342.899c-18.789 18.789-46.972 18.789-65.761 0s-18.789-46.972 0-65.761l422.752-422.752c0 0 0 0 0 0v0c0 0 0 0 0 0v0c0 0 0 0 0 0s0 0 0 0 0 0 0 0v0c0 0 0 0 0 0v0c0 0 0 0 0 0 4.697-4.697 9.394-9.394 14.092-9.394 9.394-4.697 14.092-4.697 18.789-4.697 0 0 0 0 0 0v0c0 0 0 0 4.697 0v0c0 0 0 0 0 0 4.697 0 9.394 0 14.092 4.697 4.697 0 9.394 4.697 14.092 9.394v0l422.752 422.752c14.092 9.394 18.789 23.486 18.789 32.881z"
        ],
        "attrs": [
          {}
        ],
        "width": 944,
        "isMulticolor": false,
        "isMulticolor2": false,
        "grid": 0,
        "tags": [
          "arrow-2-up"
        ],
        "colorPermutations": {
          "16821217512542542541611101": [
            {}
          ]
        }
      },
      "attrs": [
        {}
      ],
      "properties": {
        "order": 64,
        "id": 20,
        "name": "arrow-2-up",
        "prevSize": 32
      },
      "setIdx": 0,
      "setId": 2,
      "iconIdx": 9
    },
    {
      "icon": {
        "paths": [
          "M307.639 0v830.627l-237.322-237.322-70.318 74.712 360.378 355.983 355.983-355.983-70.318-74.712-237.322 237.322v-830.627z"
        ],
        "attrs": [
          {}
        ],
        "width": 716,
        "isMulticolor": false,
        "isMulticolor2": false,
        "grid": 0,
        "tags": [
          "arrow-3-down"
        ],
        "colorPermutations": {
          "16821217512542542541611101": [
            {}
          ]
        }
      },
      "attrs": [
        {}
      ],
      "properties": {
        "order": 65,
        "id": 19,
        "name": "arrow-3-down",
        "prevSize": 32
      },
      "setIdx": 0,
      "setId": 2,
      "iconIdx": 10
    },
    {
      "icon": {
        "paths": [
          "M1463.755 439.755h-1181.055l332.957-339.239-100.515-100.515-515.141 515.141 515.141 508.859 100.515-100.515-332.957-339.239h1181.055z"
        ],
        "attrs": [
          {}
        ],
        "width": 1464,
        "isMulticolor": false,
        "isMulticolor2": false,
        "grid": 0,
        "tags": [
          "arrow-3-left"
        ],
        "colorPermutations": {
          "16821217512542542541611101": [
            {}
          ]
        }
      },
      "attrs": [
        {}
      ],
      "properties": {
        "order": 66,
        "id": 18,
        "name": "arrow-3-left",
        "prevSize": 32
      },
      "setIdx": 0,
      "setId": 2,
      "iconIdx": 11
    },
    {
      "icon": {
        "paths": [
          "M0 584.245h1187.337l-339.239 339.239 106.798 100.515 508.859-508.859-508.859-515.141-106.798 100.515 339.239 339.239h-1187.337z"
        ],
        "attrs": [
          {}
        ],
        "width": 1464,
        "isMulticolor": false,
        "isMulticolor2": false,
        "grid": 0,
        "tags": [
          "arrow-3-right"
        ],
        "colorPermutations": {
          "16821217512542542541611101": [
            {}
          ]
        }
      },
      "attrs": [
        {}
      ],
      "properties": {
        "order": 67,
        "id": 17,
        "name": "arrow-3-right",
        "prevSize": 32
      },
      "setIdx": 0,
      "setId": 2,
      "iconIdx": 12
    },
    {
      "icon": {
        "paths": [
          "M408.721 1024v-826.232l237.322 232.927 70.318-70.318-355.983-360.378-360.378 360.378 70.318 70.318 237.322-232.927v826.232z"
        ],
        "attrs": [
          {}
        ],
        "width": 716,
        "isMulticolor": false,
        "isMulticolor2": false,
        "grid": 0,
        "tags": [
          "arrow-3-up"
        ],
        "colorPermutations": {
          "16821217512542542541611101": [
            {}
          ]
        }
      },
      "attrs": [
        {}
      ],
      "properties": {
        "order": 68,
        "id": 16,
        "name": "arrow-3-up",
        "prevSize": 32
      },
      "setIdx": 0,
      "setId": 2,
      "iconIdx": 13
    },
    {
      "icon": {
        "paths": [
          "M591.644 0l98.607 113.778-379.259 326.163h5787.496v151.704h-5787.496l379.259 318.578-98.607 113.778-530.963-455.111c-22.756-15.17-37.926-37.926-60.681-53.096 22.756-22.756 37.926-37.926 60.681-60.681l530.963-455.111z"
        ],
        "attrs": [
          {}
        ],
        "width": 6098,
        "isMulticolor": false,
        "isMulticolor2": false,
        "grid": 0,
        "tags": [
          "arrow-left"
        ],
        "colorPermutations": {
          "16821217512542542541611101": [
            {}
          ]
        }
      },
      "attrs": [
        {}
      ],
      "properties": {
        "order": 69,
        "id": 15,
        "name": "arrow-left",
        "prevSize": 32
      },
      "setIdx": 0,
      "setId": 2,
      "iconIdx": 14
    },
    {
      "icon": {
        "paths": [
          "M5514.43 1024l-106.193-113.778 371.674-318.578h-5779.911v-151.704h5787.496l-371.674-318.578 98.607-121.363 530.963 455.111c22.756 15.17 37.926 37.926 60.681 53.096-22.756 22.756-37.926 37.926-60.681 60.681l-530.963 455.111z"
        ],
        "attrs": [
          {}
        ],
        "width": 6098,
        "isMulticolor": false,
        "isMulticolor2": false,
        "grid": 0,
        "tags": [
          "arrow-right"
        ],
        "colorPermutations": {
          "16821217512542542541611101": [
            {}
          ]
        }
      },
      "attrs": [
        {}
      ],
      "properties": {
        "order": 70,
        "id": 14,
        "name": "arrow-right",
        "prevSize": 32
      },
      "setIdx": 0,
      "setId": 2,
      "iconIdx": 15
    },
    {
      "icon": {
        "paths": [
          "M839.344 95.126h-44.765v-95.126h-95.126v95.126h-464.437v-95.126h-95.126v95.126h-44.765c-50.361 0-95.126 39.169-95.126 89.53v744.219c0 50.361 44.765 95.126 95.126 95.126h744.219c50.361 0 95.126-44.765 95.126-95.126v-744.219c0-50.361-44.765-89.53-95.126-89.53zM839.344 934.47h-744.219v-609.923h744.219v609.923z"
        ],
        "attrs": [
          {}
        ],
        "width": 934,
        "isMulticolor": false,
        "isMulticolor2": false,
        "grid": 0,
        "tags": [
          "calendar"
        ],
        "colorPermutations": {
          "16821217512542542541611101": [
            {}
          ]
        }
      },
      "attrs": [
        {}
      ],
      "properties": {
        "order": 71,
        "id": 13,
        "name": "calendar",
        "prevSize": 32
      },
      "setIdx": 0,
      "setId": 2,
      "iconIdx": 16
    },
    {
      "icon": {
        "paths": [
          "M1064.448 710.154c-76.969 0-151.439-11.474-220.897-32.123-21.903-6.886-46.31-1.72-63.206 13.768l-98.248 113.004c-177.094-77.44-342.925-223.713-431.16-391.789l122.026-95.223c16.896-16.061 21.902-38.433 15.019-58.51-23.154-63.673-35.044-131.935-35.044-202.491 0-30.976-28.16-56.79-61.952-56.79h-216.519c-33.792 0-74.467 13.767-74.467 56.79 0 532.901 483.726 975.746 1064.448 975.746 44.431 0 61.952-36.142 61.952-67.692v-197.898c0-30.976-28.16-56.791-61.952-56.791z"
        ],
        "attrs": [
          {}
        ],
        "width": 1126,
        "isMulticolor": false,
        "isMulticolor2": false,
        "grid": 0,
        "tags": [
          "call"
        ],
        "colorPermutations": {
          "16821217512542542541611101": [
            {}
          ]
        }
      },
      "attrs": [
        {}
      ],
      "properties": {
        "order": 72,
        "id": 12,
        "name": "call",
        "prevSize": 32
      },
      "setIdx": 0,
      "setId": 2,
      "iconIdx": 17
    },
    {
      "icon": {
        "paths": [
          "M943.158 1024l-943.158-1024h1859.368l-916.211 1024z"
        ],
        "attrs": [
          {}
        ],
        "width": 1859,
        "isMulticolor": false,
        "isMulticolor2": false,
        "grid": 0,
        "tags": [
          "caret-down"
        ],
        "colorPermutations": {
          "16821217512542542541611101": [
            {}
          ]
        }
      },
      "attrs": [
        {}
      ],
      "properties": {
        "order": 73,
        "id": 11,
        "name": "caret-down",
        "prevSize": 32
      },
      "setIdx": 0,
      "setId": 2,
      "iconIdx": 18
    },
    {
      "icon": {
        "paths": [
          "M943.158 0l943.158 1024h-1886.316l943.158-1024z"
        ],
        "attrs": [
          {}
        ],
        "width": 1859,
        "isMulticolor": false,
        "isMulticolor2": false,
        "grid": 0,
        "tags": [
          "caret-up"
        ],
        "colorPermutations": {
          "16821217512542542541611101": [
            {}
          ]
        }
      },
      "attrs": [
        {}
      ],
      "properties": {
        "order": 74,
        "id": 10,
        "name": "caret-up",
        "prevSize": 32
      },
      "setIdx": 0,
      "setId": 2,
      "iconIdx": 19
    },
    {
      "icon": {
        "paths": [
          "M870.928 453.938l-427.546 427.546c-84.454 84.454-216.412 84.454-300.866 0s-84.454-216.412 0-300.866l464.495-464.495c52.784-52.784 137.237-52.784 184.742 0 52.784 52.784 52.784 137.237 0 184.742l-390.598 390.598c-21.113 21.113-52.784 21.113-73.897 0s-21.113-52.784 0-73.897l353.649-353.649-52.784-52.784-353.649 353.649c-52.784 52.784-52.784 137.237 0 184.742 52.784 52.784 137.237 52.784 184.742 0l390.598-390.598c84.454-84.454 84.454-216.412 0-300.866s-216.412-84.454-300.866 0l-464.495 469.773c-110.845 110.845-110.845 295.588 0 411.711 110.845 110.845 295.588 110.845 411.711 0l427.546-427.546-52.784-58.062z"
        ],
        "attrs": [
          {}
        ],
        "width": 924,
        "isMulticolor": false,
        "isMulticolor2": false,
        "grid": 0,
        "tags": [
          "file"
        ],
        "colorPermutations": {
          "16821217512542542541611101": [
            {}
          ]
        }
      },
      "attrs": [
        {}
      ],
      "properties": {
        "order": 75,
        "id": 9,
        "name": "file",
        "prevSize": 32
      },
      "setIdx": 0,
      "setId": 2,
      "iconIdx": 20
    },
    {
      "icon": {
        "paths": [
          "M1064.339 0l-3.103 1024h4893.479l3.103-1024h-4893.479zM2063.515 524.412c0 124.121-34.133 223.418-105.503 294.788s-167.564 108.606-288.582 108.606c-37.236 0-71.37-3.103-105.503-12.412s-65.164-18.618-93.091-34.133c-65.164-34.133-114.812-83.782-148.945-148.945-34.133-62.061-52.752-133.43-52.752-214.109 0-65.164 9.309-124.121 31.030-176.873s52.752-99.297 96.194-139.636c37.236-34.133 77.576-58.958 124.121-77.576s99.297-24.824 158.255-24.824c74.473 0 142.739 12.412 198.594 40.339s102.4 68.267 139.636 124.121l-77.576 62.061c-27.927-46.545-65.164-83.782-105.503-108.606-43.442-24.824-93.091-37.236-148.945-37.236-93.091 0-167.564 31.030-223.418 93.091s-86.885 142.739-86.885 242.036c0 93.091 27.927 170.667 86.885 232.727 58.958 58.958 133.43 89.988 223.418 89.988 80.679 0 145.842-24.824 198.594-71.37s80.679-111.709 86.885-186.182h-232.727v-83.782h325.818v27.927zM2640.679 204.8h-223.418v701.285h-96.194v-701.285h-223.418v-89.988h543.030v89.988zM3354.376 906.085h-96.194v-397.188h-418.909v397.188h-93.091v-791.273h93.091v304.097h418.909v-304.097h96.194v791.273zM3937.745 906.085l-288.582-375.467h-12.412v375.467h-93.091v-791.273h186.182c52.752 0 93.091 3.103 117.915 9.309s46.545 15.515 65.164 31.030c24.824 18.618 40.339 43.442 55.855 74.473 12.412 31.030 18.618 65.164 18.618 102.4 0 65.164-18.618 114.812-55.855 145.842-37.236 34.133-89.988 49.648-158.255 49.648h-18.618l300.994 375.467h-117.915zM4555.248 201.697h-322.715v226.521h322.715v86.885h-322.715v300.994h322.715v86.885h-415.806v-788.17h415.806v86.885zM5132.412 201.697h-322.715v226.521h322.715v86.885h-322.715v300.994h322.715v86.885h-415.806v-788.17h415.806v86.885zM5666.133 859.539c-46.545 43.442-108.606 65.164-183.079 65.164-62.061 0-114.812-15.515-158.255-46.545s-71.37-77.576-83.782-136.533l83.782-43.442c12.412 46.545 31.030 83.782 55.855 108.606 27.927 24.824 58.958 37.236 99.297 37.236 46.545 0 86.885-12.412 114.812-40.339s43.442-62.061 43.442-105.503c0-34.133-9.309-65.164-31.030-93.091-21.721-24.824-49.648-46.545-93.091-65.164l-96.194-40.339c-52.752-21.721-93.091-49.648-117.915-83.782s-37.236-74.473-37.236-124.121c0-55.855 21.721-102.4 62.061-139.636s96.194-55.855 161.358-55.855c46.545 0 89.988 9.309 124.121 31.030 34.133 18.618 62.061 49.648 80.679 89.988l-77.576 49.648c-18.618-31.030-37.236-52.752-58.958-68.267s-46.545-21.721-74.473-21.721c-34.133 0-65.164 9.309-86.885 31.030s-34.133 49.648-34.133 83.782c0 27.927 9.309 52.752 24.824 71.37 18.618 21.721 43.442 37.236 80.679 55.855l111.709 49.648c52.752 21.721 89.988 49.648 117.915 86.885 24.824 37.236 40.339 80.679 40.339 130.327 0 71.37-24.824 127.224-68.267 173.77z",
          "M3894.303 332.024c0-49.648-12.412-86.885-37.236-105.503-24.824-21.721-74.473-31.030-145.842-31.030h-71.37v263.758h71.37c74.473 0 124.121-9.309 148.945-27.927 21.721-18.618 34.133-52.752 34.133-99.297z",
          "M0 12.412v754.036h505.794v-111.709h-403.394v-86.885h806.788v341.333h-909.188v108.606h1011.588v-760.242h-505.794v108.606h403.394v89.988h-806.788v-341.333h909.188v-108.606h-1011.588z"
        ],
        "attrs": [
          {},
          {},
          {}
        ],
        "width": 5958,
        "isMulticolor": false,
        "isMulticolor2": false,
        "grid": 0,
        "tags": [
          "logo"
        ],
        "colorPermutations": {
          "16821217512542542541611101": [
            {},
            {},
            {}
          ]
        }
      },
      "attrs": [
        {},
        {},
        {}
      ],
      "properties": {
        "order": 76,
        "id": 8,
        "name": "logo",
        "prevSize": 32
      },
      "setIdx": 0,
      "setId": 2,
      "iconIdx": 21
    },
    {
      "icon": {
        "paths": [
          "M6107.429 0h-5016.408l-3.094 1024h5016.393l3.109-1024z",
          "M1781.526 498.015h334.519v26.496c0 124.208-36.125 222.277-108.551 294.232-72.408 71.943-171.129 107.82-296.309 107.82-38.203 0-74.503-3.855-108.917-11.772-34.611-7.907-66.373-19.507-95.495-34.586-66.56-35.525-117.998-84.652-154.123-147.397-36.103-62.742-54.257-133.961-54.257-213.819 0-65.686 10.774-125.122 32.325-178.117 21.742-52.995 54.276-99.732 97.77-139.845 36.677-33.865 79.045-59.436 127.448-76.552 48.41-17.299 101.925-25.948 160.731-25.948 77.915 0 145.419 13.798 202.723 41.222 57.293 27.596 104.752 69.001 142.38 124.205l-80.925 63.12c-29.122-47.846-65.62-83.543-109.115-107.466-43.483-23.923-94.171-35.879-151.848-35.879-94.171 0-170.565 30.913-229.182 92.741-58.818 61.828-88.126 142.602-88.126 242.519 0 94.215 29.872 171.498 89.45 231.852 59.571 60.35 135.578 90.533 227.858 90.533 81.32 0 149.007-23.921 203.085-71.951 54.089-48.022 84.151-110.398 90.017-187.315h-231.457v-84.092zM2380.965 905.593v-699.783h-229.38v-89.435h555.205v89.435h-228.253v699.783h-97.573zM2814.384 905.593v-789.218h96.435v303.622h430.954v-303.622h98.147v789.218h-98.147v-396.171h-430.954v396.171h-96.435zM3633.737 905.593v-789.218h190.427c54.455 0 94.171 2.952 119.515 8.833 25.307 6.075 47.616 16.2 66.743 30.547 23.991 18.214 42.715 42.87 55.954 73.601 13.422 30.731 20.041 64.779 20.041 102.134 0 64.586-18.505 113.712-55.771 147.384-37.047 33.671-91.538 50.421-163.182 50.421h-17.225l309.943 376.298h-122.514l-295.973-376.298h-13.787v376.298h-94.171zM3727.909 195.685v264.048h73.582c75.41 0 125.915-9.381 151.442-28.328 25.527-18.772 38.181-51.712 38.181-98.815 0-50.604-13.019-86.117-39.314-106.54-26.295-20.24-76.398-30.365-150.309-30.365h-73.582zM4240.933 905.593v-789.218h427.739v85.751h-331.301v226.327h331.301v87.409h-331.301v302.321h331.301v87.409h-427.739zM4832.037 905.593v-789.218h427.739v85.751h-331.301v226.327h331.301v87.409h-331.301v302.321h331.301v87.409h-427.739zM5718.345 467.284c52.773 21.899 92.672 50.97 119.515 87.216 26.661 36.44 40.082 79.309 40.082 128.816 0 72.675-23.625 131.193-71.095 175.539s-110.446 66.611-188.709 66.611c-63.927 0-117.431-15.824-160.731-47.664-43.118-31.828-72.229-77.089-87.369-135.611l87.369-42.138c11.886 47.846 31.378 84.092 58.441 108.562 27.209 24.656 61.257 36.992 102.29 36.992 48.384 0 87.552-13.616 117.431-40.664 29.842-27.242 44.8-62.387 44.8-105.991 0-35.145-10.386-65.876-31.195-91.824-20.992-26.134-52.37-48.029-94.537-66.063l-98.523-41.026c-53.906-21.899-94.171-50.055-120.466-84.652-26.478-34.406-39.717-75.81-39.717-123.84 0-56.119 21.358-102.489 64.293-139.101 42.752-36.623 97.39-55.020 163.95-55.020 48.786 0 90.953 10.114 126.501 30.17 35.767 20.057 63.561 49.871 83.419 89.068l-79.799 49.495c-17.993-30.548-38.4-53.178-60.891-68.086-22.528-14.908-48.055-22.447-76.398-22.447-36.133 0-65.829 10.857-88.905 32.389-23.040 21.521-34.597 48.945-34.597 82.433 0 27.973 8.887 52.262 26.697 72.685 17.554 20.604 45.166 38.638 82.432 54.459l115.712 49.69z",
          "M0 6.143h1037.674v109.070h-931.961v342.259h826.258v-89.746h-413.842v-109.059h519.545v759.197h-1037.674v-109.071h931.972v-342.261h-826.258v89.757h413.864v109.063h-519.578v-759.209z",
          "M519.036 127.822h518.649v12.559h-518.649v-12.559z",
          "M0.429 778.536h518.652v12.559h-518.652v-12.559z",
          "M519.036 204.964h518.649v12.549h-518.649v-12.549z",
          "M0.429 855.643h518.652v12.559h-518.652v-12.559z",
          "M519.036 154.393h518.649v12.56h-518.649v-12.56z",
          "M0.429 805.105h518.652v12.562h-518.652v-12.562z",
          "M519.036 231.536h518.649v12.56h-518.649v-12.56z",
          "M0.429 882.249h518.652v12.559h-518.652v-12.559z",
          "M519.036 180.929h518.649v12.559h-518.649v-12.559z",
          "M0.429 831.609h518.652v12.559h-518.652v-12.559z"
        ],
        "attrs": [
          {
            "fill": "rgb(0, 61, 110)"
          },
          {
            "fill": "rgb(254, 254, 254)"
          },
          {
            "fill": "rgb(0, 61, 110)"
          },
          {
            "fill": "rgb(168, 212, 175)"
          },
          {
            "fill": "rgb(168, 212, 175)"
          },
          {
            "fill": "rgb(168, 212, 175)"
          },
          {
            "fill": "rgb(168, 212, 175)"
          },
          {
            "fill": "rgb(168, 212, 175)"
          },
          {
            "fill": "rgb(168, 212, 175)"
          },
          {
            "fill": "rgb(168, 212, 175)"
          },
          {
            "fill": "rgb(168, 212, 175)"
          },
          {
            "fill": "rgb(168, 212, 175)"
          },
          {
            "fill": "rgb(168, 212, 175)"
          }
        ],
        "width": 6107,
        "isMulticolor": true,
        "isMulticolor2": false,
        "grid": 0,
        "tags": [
          "logo-color"
        ],
        "colorPermutations": {
          "16821217512542542541611101": [
            {
              "f": 0
            },
            {
              "f": 2
            },
            {
              "f": 0
            },
            {
              "f": 1
            },
            {
              "f": 1
            },
            {
              "f": 1
            },
            {
              "f": 1
            },
            {
              "f": 1
            },
            {
              "f": 1
            },
            {
              "f": 1
            },
            {
              "f": 1
            },
            {
              "f": 1
            },
            {
              "f": 1
            }
          ]
        }
      },
      "attrs": [
        {
          "fill": "rgb(0, 61, 110)"
        },
        {
          "fill": "rgb(254, 254, 254)"
        },
        {
          "fill": "rgb(0, 61, 110)"
        },
        {
          "fill": "rgb(168, 212, 175)"
        },
        {
          "fill": "rgb(168, 212, 175)"
        },
        {
          "fill": "rgb(168, 212, 175)"
        },
        {
          "fill": "rgb(168, 212, 175)"
        },
        {
          "fill": "rgb(168, 212, 175)"
        },
        {
          "fill": "rgb(168, 212, 175)"
        },
        {
          "fill": "rgb(168, 212, 175)"
        },
        {
          "fill": "rgb(168, 212, 175)"
        },
        {
          "fill": "rgb(168, 212, 175)"
        },
        {
          "fill": "rgb(168, 212, 175)"
        }
      ],
      "properties": {
        "order": 77,
        "id": 7,
        "name": "logo-color",
        "prevSize": 32
      },
      "setIdx": 0,
      "setId": 2,
      "iconIdx": 22
    },
    {
      "icon": {
        "paths": [
          "M0 6.143h1037.674v109.070h-931.961v342.259h826.258v-89.746h-413.842v-109.059h519.545v759.197h-1037.674v-109.071h931.972v-342.261h-826.258v89.757h413.864v109.063h-519.578v-759.209z",
          "M519.036 127.857h518.649v12.559h-518.649v-12.559z",
          "M0.429 778.573h518.652v12.559h-518.652v-12.559z",
          "M519.036 204.929h518.649v12.548h-518.649v-12.548z",
          "M0.429 855.643h518.652v12.559h-518.652v-12.559z",
          "M519.036 154.429h518.649v12.559h-518.649v-12.559z",
          "M0.429 805.072h518.652v12.559h-518.652v-12.559z",
          "M519.036 231.571h518.649v12.56h-518.649v-12.56z",
          "M0.429 882.286h518.652v12.559h-518.652v-12.559z",
          "M519.036 180.929h518.649v12.559h-518.649v-12.559z",
          "M0.429 831.572h518.652v12.559h-518.652v-12.559z"
        ],
        "attrs": [
          {
            "fill": "rgb(0, 61, 110)"
          },
          {
            "fill": "rgb(168, 212, 175)"
          },
          {
            "fill": "rgb(168, 212, 175)"
          },
          {
            "fill": "rgb(168, 212, 175)"
          },
          {
            "fill": "rgb(168, 212, 175)"
          },
          {
            "fill": "rgb(168, 212, 175)"
          },
          {
            "fill": "rgb(168, 212, 175)"
          },
          {
            "fill": "rgb(168, 212, 175)"
          },
          {
            "fill": "rgb(168, 212, 175)"
          },
          {
            "fill": "rgb(168, 212, 175)"
          },
          {
            "fill": "rgb(168, 212, 175)"
          }
        ],
        "width": 1061,
        "isMulticolor": true,
        "isMulticolor2": false,
        "grid": 0,
        "tags": [
          "logo-small"
        ],
        "colorPermutations": {
          "16821217512542542541611101": [
            {
              "f": 0
            },
            {
              "f": 1
            },
            {
              "f": 1
            },
            {
              "f": 1
            },
            {
              "f": 1
            },
            {
              "f": 1
            },
            {
              "f": 1
            },
            {
              "f": 1
            },
            {
              "f": 1
            },
            {
              "f": 1
            },
            {
              "f": 1
            }
          ]
        }
      },
      "attrs": [
        {
          "fill": "rgb(0, 61, 110)"
        },
        {
          "fill": "rgb(168, 212, 175)"
        },
        {
          "fill": "rgb(168, 212, 175)"
        },
        {
          "fill": "rgb(168, 212, 175)"
        },
        {
          "fill": "rgb(168, 212, 175)"
        },
        {
          "fill": "rgb(168, 212, 175)"
        },
        {
          "fill": "rgb(168, 212, 175)"
        },
        {
          "fill": "rgb(168, 212, 175)"
        },
        {
          "fill": "rgb(168, 212, 175)"
        },
        {
          "fill": "rgb(168, 212, 175)"
        },
        {
          "fill": "rgb(168, 212, 175)"
        }
      ],
      "properties": {
        "order": 78,
        "id": 6,
        "name": "logo-small",
        "prevSize": 32
      },
      "setIdx": 0,
      "setId": 2,
      "iconIdx": 23
    },
    {
      "icon": {
        "paths": [
          "M543.152 1024c-77.88 0-150.234-12.059-216.557-36.679-66.826-25.123-124.106-60.797-172.844-107.023-47.733-45.723-85.417-99.988-112.55-161.79-27.635-62.304-41.201-131.14-41.201-206.508 0-74.866 13.566-143.199 40.699-205.503 27.132-62.807 65.319-117.072 114.057-163.297s106.52-80.895 172.844-105.013c67.329-25.123 141.189-38.186 221.079-38.186 92.954 0 175.859 15.576 249.217 46.226 73.358 31.152 133.653 75.368 181.386 133.653l-177.366 160.283c-33.664-36.679-70.343-63.812-109.535-81.397-38.689-18.591-81.397-28.137-129.633-28.137-42.206 0-80.895 6.532-115.564 19.596s-64.314 32.157-88.432 57.782c-24.62 24.62-43.713 53.763-57.782 88.432-13.064 33.664-19.596 72.353-19.596 115.564 0 41.201 6.532 79.388 19.596 114.057 14.069 34.669 33.162 64.816 57.782 89.939 24.62 24.62 53.26 43.713 87.427 57.782 34.669 13.064 72.856 19.596 114.057 19.596s81.397-6.532 121.091-19.596c39.191-14.069 79.388-37.684 119.584-70.343l156.263 195.454c-56.275 40.196-121.594 71.348-195.454 92.954-74.866 21.605-147.219 32.157-218.567 32.157zM710.469 862.21v-371.313h246.202v407.992l-246.202-36.679z",
          "M1385.264 1004.404v-763.729h-302.477v-221.079h881.806v221.079h-300.97v763.729h-278.359z",
          "M2769.021 19.596h278.359v984.809h-278.359v-984.809zM2389.166 1004.404h-278.359v-984.809h278.359v984.809zM2788.616 620.53h-419.046v-230.626h419.046v230.626z",
          "M3286.548 1004.404v-984.809h450.198c89.939 0 167.317 14.571 232.133 43.713 65.821 29.142 116.067 71.348 151.741 126.618 35.674 54.265 53.26 119.081 53.26 193.947 0 73.861-17.586 138.175-53.26 192.942-35.674 53.26-86.422 94.964-151.741 123.604-64.816 28.137-142.194 42.206-232.133 42.206h-295.443l123.604-116.569v378.347h-278.359zM3895.521 1004.404l-244.695-358.752h296.95l246.202 358.752h-298.457zM3564.907 655.702l-123.604-128.126h278.359c58.285 0 101.496-12.561 129.633-38.186 29.142-25.123 43.713-60.294 43.713-105.515 0-45.723-14.571-81.397-43.713-107.023-28.137-25.123-71.348-38.186-129.633-38.186h-278.359l123.604-128.126v545.162z",
          "M4626.088 400.958h457.233v208.016h-457.233v-208.016zM4645.684 789.354h515.015v215.050h-790.862v-984.809h772.271v215.050h-496.424v554.709z",
          "M5613.409 400.958h457.233v208.016h-457.233v-208.016zM5633.005 789.354h515.015v215.050h-790.862v-984.809h772.773v215.050h-496.424v554.709z",
          "M6691.172 1024c-80.895 0-158.273-10.049-233.641-29.645-73.861-20.601-134.658-46.728-181.386-78.885l91.447-205.503c44.216 28.137 94.964 51.753 151.741 70.343 58.285 17.586 116.067 26.63 172.844 26.63 38.689 0 69.339-3.517 92.954-10.049 23.615-7.537 40.196-17.083 50.748-28.137 11.054-12.059 17.083-26.128 17.083-42.206 0-22.61-10.049-40.196-31.152-53.26-20.601-13.064-47.231-24.118-80.393-32.157-32.659-8.542-69.339-17.083-109.535-25.123-39.191-8.542-79.388-19.093-119.584-32.157-39.191-13.064-75.368-30.147-108.53-50.748-32.659-21.605-59.792-49.24-80.393-82.905-20.601-34.669-31.152-78.383-31.152-130.638 0-59.289 16.079-112.55 47.733-160.283 32.659-47.733 81.397-86.422 146.214-115.564s145.209-43.713 242.183-43.713c64.816 0 128.126 7.537 189.927 22.61 62.807 14.069 118.579 35.172 167.317 63.309l-85.92 207.011c-46.728-25.123-93.456-44.216-139.18-56.275-45.723-13.064-90.442-19.596-133.653-19.596-38.186 0-69.339 4.020-92.954 12.561-23.615 7.537-40.196 17.586-50.748 31.152-10.552 13.064-15.576 28.137-15.576 45.221 0 21.605 10.049 38.689 29.645 52.255 20.601 12.059 47.231 22.61 80.393 31.152 33.664 7.537 70.343 15.576 109.535 24.118 40.196 8.542 80.393 19.093 119.584 32.157 40.196 12.059 76.875 29.142 109.535 50.748 32.659 20.601 59.289 48.236 78.885 82.905 20.601 33.664 31.152 76.373 31.152 128.126 0 57.28-16.581 110.037-49.24 158.775-31.655 47.733-80.393 86.422-144.707 115.564-63.309 27.635-143.702 42.206-241.178 42.206z"
        ],
        "attrs": [
          {},
          {},
          {},
          {},
          {},
          {},
          {}
        ],
        "width": 7127,
        "isMulticolor": false,
        "isMulticolor2": false,
        "grid": 0,
        "tags": [
          "logo-title"
        ],
        "colorPermutations": {
          "16821217512542542541611101": [
            {},
            {},
            {},
            {},
            {},
            {},
            {}
          ]
        }
      },
      "attrs": [
        {},
        {},
        {},
        {},
        {},
        {},
        {}
      ],
      "properties": {
        "order": 79,
        "id": 5,
        "name": "logo-title",
        "prevSize": 32
      },
      "setIdx": 0,
      "setId": 2,
      "iconIdx": 24
    },
    {
      "icon": {
        "paths": [
          "M451.319 3.793c-166.874 18.963-318.578 125.156-394.43 280.652-15.17 34.133-26.548 56.889-34.133 94.815-30.341 113.778-18.963 231.348 26.548 337.541l7.585 18.963-30.341 144.119c-15.17 79.644-26.548 144.119-26.548 144.119s64.474-11.378 144.119-26.548l144.119-30.341 18.963 7.585c37.926 18.963 87.23 30.341 136.533 37.926 34.133 3.793 109.985 3.793 147.911 0 56.889-7.585 98.607-22.756 147.911-49.304 140.326-68.267 238.933-197.215 273.067-352.711 15.17-64.474 15.17-147.911 0-212.385-15.17-75.852-49.304-144.119-98.607-208.593-15.17-22.756-64.474-68.267-87.23-87.23-75.852-56.889-159.289-94.815-250.311-106.193-30.341 3.793-94.815 3.793-125.156 7.585zM565.096 53.096c83.437 7.585 170.667 45.511 238.933 98.607 18.963 15.17 60.681 56.889 72.059 72.059 109.985 140.326 132.741 329.956 53.096 485.452-45.511 94.815-121.363 166.874-216.178 212.385-98.607 45.511-204.8 56.889-310.993 30.341-26.548-7.585-49.304-15.17-79.644-30.341l-26.548-11.378-113.778 22.756c-64.474 11.378-117.57 22.756-117.57 22.756s11.378-53.096 22.756-117.57l22.756-117.57-11.378-26.548c-45.511-98.607-56.889-201.007-30.341-303.407 45.511-178.252 204.8-318.578 398.222-337.541 22.756-3.793 75.852-3.793 98.607 0z",
          "M360.296 273.067c7.585 3.793 60.681 56.889 72.059 68.267 15.17 18.963 11.378 30.341-7.585 53.096-34.133 37.926-41.719 87.23-18.963 132.741 7.585 11.378 15.17 18.963 41.719 49.304 26.548 26.548 37.926 34.133 49.304 41.719 18.963 11.378 34.133 15.17 53.096 15.17 30.341 0 53.096-7.585 79.644-30.341 18.963-18.963 34.133-18.963 49.304-11.378 3.793 3.793 22.756 18.963 41.719 37.926 37.926 37.926 37.926 41.719 34.133 56.889 0 7.585-26.548 37.926-45.511 49.304s-30.341 15.17-68.267 15.17c-37.926 0-60.681-3.793-91.022-11.378-94.815-22.756-174.459-83.437-223.763-163.081-18.963-30.341-34.133-64.474-41.719-102.4-7.585-30.341-11.378-53.096-11.378-91.022 0-45.511 3.793-60.681 30.341-87.23 22.756-26.548 41.719-34.133 56.889-22.756z"
        ],
        "attrs": [
          {},
          {}
        ],
        "isMulticolor": false,
        "isMulticolor2": false,
        "grid": 0,
        "tags": [
          "phone"
        ],
        "colorPermutations": {
          "16821217512542542541611101": [
            {},
            {}
          ]
        }
      },
      "attrs": [
        {},
        {}
      ],
      "properties": {
        "order": 80,
        "id": 4,
        "name": "phone",
        "prevSize": 32
      },
      "setIdx": 0,
      "setId": 2,
      "iconIdx": 25
    },
    {
      "icon": {
        "paths": [
          "M1024 102.4l-102.4-102.4-409.6 409.6-409.6-409.6-102.4 102.4 409.6 409.6-409.6 409.6 102.4 102.4 409.6-409.6 409.6 409.6 102.4-102.4-409.6-409.6 409.6-409.6z"
        ],
        "attrs": [
          {}
        ],
        "isMulticolor": false,
        "isMulticolor2": false,
        "grid": 0,
        "tags": [
          "remove"
        ],
        "colorPermutations": {
          "16821217512542542541611101": [
            {}
          ]
        }
      },
      "attrs": [
        {}
      ],
      "properties": {
        "order": 81,
        "id": 3,
        "name": "remove",
        "prevSize": 32
      },
      "setIdx": 0,
      "setId": 2,
      "iconIdx": 26
    },
    {
      "icon": {
        "paths": [
          "M273.067 0c-75.852 11.378-128.948 37.926-182.044 91.022s-83.437 113.778-91.022 189.63c-3.793 45.511 3.793 106.193 22.756 147.911 3.793 11.378 3.793 11.378 3.793 56.889s0 72.059 7.585 106.193c26.548 144.119 121.363 273.067 254.104 337.541 45.511 22.756 91.022 37.926 144.119 45.511 18.963 3.793 34.133 3.793 72.059 3.793h49.304l22.756 11.378c22.756 11.378 49.304 18.963 75.852 26.548 15.17 3.793 26.548 3.793 60.681 3.793 37.926 0 45.511 0 64.474-3.793 60.681-15.17 109.985-37.926 155.496-83.437 26.548-26.548 45.511-49.304 60.681-83.437 41.719-83.437 41.719-185.837 0-269.274l-7.585-11.378v-49.304c0-68.267-3.793-109.985-26.548-166.874-56.889-170.667-208.593-292.030-386.844-318.578-30.341-3.793-75.852-3.793-98.607-3.793h-22.756l-18.963-7.585c-37.926-15.17-75.852-22.756-121.363-22.756-18.963 0-37.926 0-37.926 0zM364.089 53.096c22.756 3.793 41.719 11.378 64.474 22.756l15.17 7.585 15.17-3.793c22.756-3.793 79.644-3.793 106.193 0 216.178 30.341 375.467 212.385 371.674 424.77 0 15.17 0 37.926-3.793 45.511l-3.793 18.963 11.378 18.963c18.963 37.926 26.548 68.267 30.341 109.985 3.793 64.474-15.17 121.363-56.889 170.667-45.511 60.681-113.778 94.815-193.422 98.607-49.304 3.793-102.4-11.378-144.119-34.133l-15.17-7.585-30.341 3.793c-72.059 3.793-151.704-11.378-216.178-41.719-49.304-22.756-79.644-45.511-117.57-83.437-60.681-60.681-98.607-136.533-117.57-219.97-7.585-37.926-7.585-98.607-3.793-136.533 3.793-11.378 0-11.378-3.793-26.548-7.585-18.963-18.963-49.304-22.756-72.059 3.793-18.963 3.793-56.889 7.585-83.437 18.963-106.193 106.193-193.422 216.178-212.385 18.963-3.793 68.267-3.793 91.022-0z",
          "M546.133 238.933c26.548 3.793 41.719 11.378 68.267 22.756 49.304 22.756 75.852 53.096 79.644 87.23 3.793 30.341-18.963 53.096-49.304 53.096-18.963 0-26.548-3.793-53.096-34.133-18.963-18.963-26.548-26.548-37.926-30.341-45.511-22.756-109.985-18.963-140.326 3.793-26.548 18.963-34.133 56.889-15.17 79.644 18.963 18.963 34.133 26.548 125.156 45.511 75.852 15.17 91.022 22.756 117.57 34.133 18.963 11.378 45.511 30.341 56.889 49.304 15.17 22.756 26.548 60.681 22.756 94.815-3.793 60.681-34.133 102.4-91.022 128.948-41.719 18.963-83.437 26.548-140.326 26.548-53.096 0-94.815-11.378-128.948-26.548-53.096-26.548-83.437-64.474-83.437-102.4 0-26.548 18.963-45.511 45.511-45.511 22.756 0 26.548 3.793 68.267 53.096 22.756 22.756 41.719 34.133 72.059 41.719 22.756 3.793 60.681 3.793 75.852-3.793 37.926-11.378 56.889-34.133 60.681-64.474 3.793-26.548-11.378-49.304-34.133-56.889-7.585-3.793-49.304-15.17-94.815-26.548-41.719-22.756-83.437-37.926-91.022-37.926-53.096-18.963-83.437-49.304-98.607-94.815-3.793-11.378-3.793-18.963-3.793-41.719 0-30.341 3.793-45.511 15.17-68.267 22.756-45.511 75.852-79.644 147.911-91.022 22.756-3.793 79.644-3.793 106.193 3.793z"
        ],
        "attrs": [
          {},
          {}
        ],
        "isMulticolor": false,
        "isMulticolor2": false,
        "grid": 0,
        "tags": [
          "skype"
        ],
        "colorPermutations": {
          "16821217512542542541611101": [
            {},
            {}
          ]
        }
      },
      "attrs": [
        {},
        {}
      ],
      "properties": {
        "order": 82,
        "id": 2,
        "name": "skype",
        "prevSize": 32
      },
      "setIdx": 0,
      "setId": 2,
      "iconIdx": 27
    },
    {
      "icon": {
        "paths": [
          "M512 1024c-281.6 0-512-230.4-512-512s230.4-512 512-512 512 230.4 512 512-230.4 512-512 512zM512 36.571c-263.314 0-475.429 212.114-475.429 475.429s212.114 475.429 475.429 475.429c263.314 0 475.429-212.114 475.429-475.429s-212.114-475.429-475.429-475.429zM629.029 775.314c-3.657 0-7.314 0-10.971-3.657l-117.029-87.771-117.029 87.771c-7.314 3.657-14.629 7.314-21.943 14.629-3.657-7.314-3.657-14.629-7.314-21.943l-73.143-201.143-120.686-47.543c-7.314-3.657-14.629-10.971-14.629-18.286s3.657-14.629 10.971-18.286l592.457-234.057c7.314-3.657 14.629 0 18.286 3.657s7.314 10.971 7.314 18.286l-128 493.714c0 7.314-7.314 10.971-10.971 10.971-3.657 3.657-3.657 3.657-7.314 3.657zM512 647.314l106.057 80.457 113.371-431.543-515.657 201.143 76.8 32.914 299.886-153.6c7.314-3.657 18.286 0 21.943 3.657s3.657 18.286 0 21.943l-168.229 193.829 65.829 51.2zM431.543 632.686l-25.6 76.8 62.171-47.543-36.571-29.257zM318.171 559.543l54.857 142.629 36.571-106.057c0 0 3.657-3.657 3.657-7.314l120.686-138.971-215.771 109.714z"
        ],
        "attrs": [
          {}
        ],
        "isMulticolor": false,
        "isMulticolor2": false,
        "grid": 0,
        "tags": [
          "telegram"
        ],
        "colorPermutations": {
          "16821217512542542541611101": [
            {}
          ]
        }
      },
      "attrs": [
        {}
      ],
      "properties": {
        "order": 83,
        "id": 1,
        "name": "telegram",
        "prevSize": 32
      },
      "setIdx": 0,
      "setId": 2,
      "iconIdx": 28
    },
    {
      "icon": {
        "paths": [
          "M356.504 0c-64.474 3.793-144.119 15.17-166.874 18.963-45.511 11.378-79.644 34.133-113.778 68.267s-56.889 75.852-64.474 125.156c-7.585 41.719-15.17 231.348-11.378 329.956 3.793 64.474 3.793 106.193 7.585 125.156 7.585 56.889 41.719 117.57 91.022 151.704 37.926 30.341 75.852 41.719 136.533 49.304l22.756 3.793v75.852c0 72.059 0 75.852 3.793 75.852 0 0 56.889-30.341 121.363-72.059l121.363-68.267h18.963c11.378 0 41.719-3.793 64.474-3.793 83.437-3.793 155.496-11.378 185.837-22.756 79.644-22.756 144.119-94.815 163.081-182.044 7.585-34.133 11.378-109.985 11.378-238.933 0-125.156-3.793-197.215-11.378-231.348-11.378-49.304-34.133-91.022-68.267-128.948-26.548-26.548-60.681-45.511-98.607-56.889-26.548-7.585-98.607-15.17-185.837-22.756-37.926 3.793-185.837 3.793-227.556 3.793zM538.548 45.511c79.644 0 182.044 11.378 212.385 18.963 64.474 15.17 117.57 68.267 136.533 132.741 11.378 34.133 15.17 94.815 15.17 246.519 0 204.8-3.793 242.726-41.719 295.822-11.378 18.963-34.133 41.719-53.096 53.096-15.17 11.378-37.926 18.963-53.096 26.548-30.341 7.585-128.948 18.963-227.556 22.756h-37.926l-94.815 53.096c-49.304 26.548-91.022 53.096-91.022 53.096s0-26.548 0-56.889v-56.889l-45.511-3.793c-26.548-3.793-53.096-7.585-60.681-7.585-53.096-15.17-98.607-49.304-121.363-98.607-15.17-30.341-18.963-49.304-22.756-98.607-7.585-117.57-7.585-288.237 0-383.052 7.585-91.022 75.852-159.289 163.081-178.252 11.378-3.793 79.644-11.378 117.57-15.17 30.341-3.793 132.741-3.793 144.119-3.793 7.585 0 34.133 0 60.681 0z",
          "M474.074 178.252h11.378c30.341 0 72.059 11.378 102.4 26.548 68.267 34.133 106.193 91.022 117.57 174.459 0 11.378 3.793 26.548 3.793 30.341v11.378h45.511v-22.756c-7.585-113.778-64.474-201.007-159.289-242.726-30.341-15.17-75.852-22.756-106.193-22.756h-15.17v45.511z",
          "M474.074 265.481h11.378c15.17 0 41.719 3.793 56.889 11.378 49.304 18.963 75.852 64.474 83.437 125.156v18.963h45.511v-7.585c0-15.17-3.793-49.304-11.378-64.474-22.756-75.852-83.437-117.57-163.081-125.156h-18.963v41.719z",
          "M474.074 352.711h11.378c34.133 3.793 45.511 15.17 49.304 49.304l3.793 15.17h45.511v-15.17c-3.793-30.341-11.378-49.304-26.548-68.267-15.17-15.17-37.926-26.548-68.267-26.548h-15.17v45.511z",
          "M295.822 250.311c11.378 7.585 64.474 60.681 64.474 68.267 3.793 7.585 3.793 18.963 0 22.756 0 3.793-7.585 11.378-15.17 18.963-18.963 22.756-26.548 41.719-26.548 72.059 0 22.756 3.793 41.719 15.17 56.889 3.793 7.585 18.963 26.548 37.926 41.719 37.926 37.926 53.096 45.511 87.23 45.511 26.548 0 49.304-7.585 68.267-26.548 15.17-11.378 18.963-15.17 34.133-15.17 7.585 0 75.852 68.267 79.644 79.644s0 18.963-18.963 41.719c-26.548 26.548-49.304 34.133-94.815 34.133-109.985-7.585-201.007-56.889-261.689-147.911-34.133-53.096-53.096-117.57-53.096-189.63 0-34.133 7.585-53.096 30.341-79.644 26.548-30.341 37.926-34.133 53.096-22.756z"
        ],
        "attrs": [
          {},
          {},
          {},
          {},
          {}
        ],
        "width": 948,
        "isMulticolor": false,
        "isMulticolor2": false,
        "grid": 0,
        "tags": [
          "viber"
        ],
        "colorPermutations": {
          "16821217512542542541611101": [
            {},
            {},
            {},
            {},
            {}
          ]
        }
      },
      "attrs": [
        {},
        {},
        {},
        {},
        {}
      ],
      "properties": {
        "order": 84,
        "id": 0,
        "name": "viber",
        "prevSize": 32
      },
      "setIdx": 0,
      "setId": 2,
      "iconIdx": 29
    }
  ],
  "height": 1024,
  "preferences": {
    "showGlyphs": true,
    "showQuickUse": true,
    "showQuickUse2": true,
    "showSVGs": true,
    "fontPref": {
      "prefix": "icon-",
      "metadata": {
        "fontFamily": "icomoon"
      },
      "metrics": {
        "emSize": 1024,
        "baseline": 6.25,
        "whitespace": 50
      },
      "embed": false
    },
    "imagePref": {
      "prefix": "icon-",
      "png": true,
      "useClassSelector": true,
      "color": 0,
      "bgColor": 16777215,
      "classSelector": ".icon",
      "name": "icomoon"
    },
    "historySize": 50,
    "showCodes": true,
    "gridSize": 16
  }
}